mangleframes/__init__.py
mangleframes/alerts.py
mangleframes/launcher.py
mangleframes/session.py
mangleframes-0.3.4.data/scripts/mangleframes-viewer
mangleframes-0.3.4.data/scripts/spark-connect-proxy
mangleframes-0.3.4.dist-info/METADATA
mangleframes-0.3.4.dist-info/WHEEL
mangleframes-0.3.4.dist-info/licenses/LICENSE
mangleframes-0.3.4.dist-info/RECORD
