Metadata-Version: 2.4
Name: mangleframes
Version: 0.3.4
Classifier: Programming Language :: Python :: 3
Classifier: Programming Language :: Rust
Classifier: License :: OSI Approved :: MIT License
Requires-Dist: pyspark>=3.5.0
Requires-Dist: loguru>=0.7.3
Requires-Dist: maturin[patchelf]>=1.11.2
Requires-Dist: pyarrow>=11.0.0
Requires-Dist: python-dateutil>=2.8.0
Requires-Dist: grpcio>=1.76.0
Requires-Dist: grpcio-status>=1.76.0
Requires-Dist: zstandard>=0.25.0
Requires-Dist: pandas>=2.3.3
Requires-Dist: pytest>=7.0 ; extra == 'dev'
Requires-Dist: maturin>=1.4 ; extra == 'dev'
Provides-Extra: dev
License-File: LICENSE
Summary: PySpark DataFrame viewer with modern web UI
License: MIT
Requires-Python: >=3.12
